<?xml version="1.0" encoding="UTF-8" standalone="no"?>
<databaseChangeLog
		xmlns="http://www.liquibase.org/xml/ns/dbchangelog"
		xmlns:xsi="http://www.w3.org/2001/XMLSchema-instance"
		xsi:schemaLocation="http://www.liquibase.org/xml/ns/dbchangelog http://www.liquibase.org/xml/ns/dbchangelog/dbchangelog-3.4.xsd">
	<changeSet author="GMALEWICZ (generated)" id="1736866558381-22">
		<addColumn tableName="cycle">
			<column name="series" type="INTEGER" defaultValue="1">
				<constraints nullable="false" />
			</column>
		</addColumn>
	</changeSet>
	<changeSet author="GMALEWICZ (generated)" id="1736866558381-23">
		<addColumn tableName="cycle_result">
			<column name="series" type="INTEGER" defaultValue="1">
				<constraints nullable="false" />
			</column>
		</addColumn>
	</changeSet>
</databaseChangeLog>
